hackcaptcha/__init__.py
hackcaptcha/crackers.py
hackcaptcha/algorithms/__init__.py
hackcaptcha/algorithms/click/__init__.py
hackcaptcha/algorithms/click/zt12306.py
hackcaptcha/algorithms/digital/__init__.py
hackcaptcha/algorithms/slider/__init__.py
hackcaptcha/algorithms/slider/canny.py
hackcaptcha/webapis/__init__.py
hackcaptcha/webapis/click/__init__.py
hackcaptcha/webapis/digital/__init__.py
hackcaptcha/webapis/digital/baidu.py
hackcaptcha/webapis/slider/__init__.py
hackcaptcha-0.0.1.dist-info/LICENSE
hackcaptcha-0.0.1.dist-info/METADATA
hackcaptcha-0.0.1.dist-info/WHEEL
hackcaptcha-0.0.1.dist-info/top_level.txt
hackcaptcha-0.0.1.dist-info/zip-safe
hackcaptcha-0.0.1.dist-info/RECORD
