Metadata-Version: 2.1
Name: hackcaptcha
Version: 0.0.1
Summary: Provide api functions for captcha recognition.
Home-page: https://github.com/CharlesPikachu/hackcaptcha
Author: Charles
Author-email: charlesjzc@qq.com
License: MIT
Platform: UNKNOWN
Classifier: License :: OSI Approved :: MIT License
Classifier: Programming Language :: Python :: 3
Classifier: Intended Audience :: Developers
Classifier: Operating System :: OS Independent
Requires-Dist: opencv-python (>=4.1.2)
Requires-Dist: requests (>=2.22.0)
Requires-Dist: keras (>=2.2.4)
Requires-Dist: numpy (>=1.16.2)
